pyosrm.cpython-35m-x86_64-linux-gnu.so
.libspyosrm/libboost_system-762e0962.so.1.54.0
.libspyosrm/libboost_iostreams-5b527283.so.1.54.0
.libspyosrm/libz-d8a329de.so.1.2.7
.libspyosrm/libbz2-a273e504.so.1.0.6
.libspyosrm/libboost_thread-75bfc3e3.so.1.54.0
.libspyosrm/libboost_filesystem-8e731c7e.so.1.54.0
pyosrm-0.0.2.dist-info/WHEEL
pyosrm-0.0.2.dist-info/METADATA
pyosrm-0.0.2.dist-info/RECORD
pyosrm-0.0.2.dist-info/top_level.txt
