Metadata-Version: 2.1
Name: pyosrm
Version: 0.0.2
Summary: Cython wrapper of osrm-backend to be used in Python
Home-page: https://github.com/enricodvn/pyosrm
Author: Enrico Davini
License: MIT
Platform: UNKNOWN
